{
  "flow_config": {
    "flow_type": "bare",
    "domain": "u1",
    "base_dist_config": {
      "dist_type": "uniform"
    },
    "layer_chain_config": {
      "layer_configs": {
        "layer_type": "coupling_layer",
        "specific_layer_config": {
          "domain": "u1",
          "specific_layer_type": "bare",
          "diffeomorphism": "ncp",
          "expressivity": 3,
          "net_config": {
            "net_type": "cnn",
            "net_hidden": [
              [
                8,
                16,
                24,
                24
              ],
              [
                8,
                16,
                16,
                24,
                24
              ],
              [
                8,
                8,
                16,
                24,
                24
              ],
              [
                8,
                16,
                24,
                32
              ],
              [
                8,
                16,
                24,
                32,
                32
              ],
              [
                8,
                8,
                8,
                8,
                8,
                8
              ],
              [
                8,
                16,
                24,
                32,
                64
              ]
            ]
          }
        },
        "num_layers": 25,
        "layer_split_config": {
          "split_type": "n_transforms",
          "specific_split_type_config": {
            "n_transformed": 1
          }
        }
      }
    }
  },
  "observables": [
    "Q",
    "Chi_t"
  ],
  "action_config": {
    "target_system": "qr",
    "action_type": "qr",
    "specific_action_config": {
      "beta": 4.0
    }
  },
  "dim": [
    25
  ],
  "trainer_config": {
    "learning_rate": 0.001,
    "auto_lr_find": false,
    "batch_size": 10000,
    "train_num_batches": 100,
    "val_num_batches": 5,
    "max_epochs": 1000,
    "log_every_n_steps": 25,
    "task_parameters": [
      "net_hidden"
    ],
    "accumulate_grad_batches": 2,
    "loss_configs": [
      {
        "loss_type": "reverse",
        "specific_loss_config": {}
      }
    ]
  }
}